{
  "nodes": [
    {
      "parameters": {
        "path": "68b13bec-9cf4-4fdb-aff2-d67c5ec00b66",
        "formTitle": "Generate Gambar Konten Otomatis",
        "formFields": {
          "values": [
            {
              "fieldLabel": "prompt"
            },
            {
              "fieldLabel": "task_type"
            },
            {
              "fieldLabel": "api_key"
            }
          ]
        },
        "options": {}
      },
      "id": "ea3505e8-b0c4-43b2-aa9d-4c5d1a20802a",
      "name": "Submit Text Prompt untuk Generate Gambar",
      "type": "n8n-nodes-base.formTrigger",
      "typeVersion": 1,
      "position": [
        -880,
        -96
      ],
      "webhookId": "68b13bec-9cf4-4fdb-aff2-d67c5ec00b66"
    },
    {
      "parameters": {
        "method": "POST",
        "url": "https://api.kie.ai/api/v1/jobs/createTask",
        "sendHeaders": true,
        "headerParameters": {
          "parameters": [
            {
              "name": "Authorization",
              "value": "=Bearer {{$node[\"Submit Text Prompt untuk Generate Gambar\"].json[\"api_key\"]}}"
            }
          ]
        },
        "sendBody": true,
        "specifyBody": "json",
        "jsonBody": "{\n  \"model\": \"grok-imagine/text-to-image\",\n  \"input\": {\n    \"prompt\": \"Cinematic wide shot of thousands of diverse people in bright neon jerseys running together on a wide city avenue during a morning 5K fun run, colorful flags and confetti in the air, modern skyscrapers in the background, bright sunny morning, highly detailed, 8k resolution.\",\n    \"aspect_ratio\": \"3:2\"\n  }\n}",
        "options": {}
      },
      "id": "dc68e0ef-902b-41ce-9ec3-ab493e675beb",
      "name": "Mengirim Image Generation Request ke..",
      "type": "n8n-nodes-base.httpRequest",
      "typeVersion": 4.1,
      "position": [
        -656,
        -96
      ]
    },
    {
      "parameters": {
        "amount": 10,
        "unit": "seconds"
      },
      "id": "acabc28f-db14-4d3a-9527-cb4ac0b8511d",
      "name": "Menunggu Proses Generate Gambar",
      "type": "n8n-nodes-base.wait",
      "typeVersion": 1,
      "position": [
        -432,
        -96
      ],
      "webhookId": "85f7c7ce-9548-47b1-9cb1-cb207e6b6639"
    },
    {
      "parameters": {
        "url": "https://api.kie.ai/api/v1/jobs/recordInfo",
        "sendQuery": true,
        "queryParameters": {
          "parameters": [
            {
              "name": "=taskId",
              "value": "={{ $('Mengirim Image Generation Request ke..').item.json.data.recordId }}"
            }
          ]
        },
        "sendHeaders": true,
        "headerParameters": {
          "parameters": [
            {
              "name": "Authorization",
              "value": "=Bearer {{$node[\"Submit Text Prompt untuk Generate Gambar\"].json[\"api_key\"]}}"
            }
          ]
        },
        "options": {}
      },
      "id": "726d295e-a018-4f7c-be95-fce8e77ee36c",
      "name": "Mendapatkan Status Generate",
      "type": "n8n-nodes-base.httpRequest",
      "typeVersion": 4.1,
      "position": [
        -224,
        -96
      ]
    },
    {
      "parameters": {
        "conditions": {
          "string": [
            {
              "value1": "={{ $json.data.state }}",
              "value2": "success"
            }
          ]
        }
      },
      "id": "7010c49b-f082-46d1-bb04-3a24ed71dce8",
      "name": "Check Jika Generate Sudah Selesai",
      "type": "n8n-nodes-base.if",
      "typeVersion": 1,
      "position": [
        16,
        -96
      ]
    },
    {
      "parameters": {
        "jsCode": "const result = JSON.parse($json.data.resultJson);\nreturn [{\n  img1: result.resultUrls[0] || null,\n  img2: result.resultUrls[1] || null,\n  img3: result.resultUrls[2] || null,\n  img4: result.resultUrls[3] || null\n}];"
      },
      "id": "ebf41ed2-e274-4bec-9fd4-e35caab80294",
      "name": "Format Result",
      "type": "n8n-nodes-base.code",
      "typeVersion": 2,
      "position": [
        272,
        -112
      ]
    },
    {
      "parameters": {
        "jsCode": "const urls = [\n  $json.img1,\n  $json.img2,\n  $json.img3,\n  $json.img4\n].filter(Boolean);\n\nreturn urls.map((url, index) => ({\n  json: {\n    url,\n    index: index + 1\n  }\n}));"
      },
      "id": "7900b005-357b-4fc5-be9a-08b867ba9652",
      "name": "Loop Image",
      "type": "n8n-nodes-base.code",
      "typeVersion": 2,
      "position": [
        496,
        -112
      ]
    },
    {
      "parameters": {
        "url": "={{$json.url}}",
        "options": {}
      },
      "id": "1a561db6-13a4-4a58-bbb6-0a42e650196c",
      "name": "Download Gambar",
      "type": "n8n-nodes-base.httpRequest",
      "typeVersion": 4.1,
      "position": [
        704,
        -112
      ]
    },
    {
      "parameters": {
        "operation": "sendPhoto",
        "chatId": "1492595082",
        "binaryData": true,
        "additionalFields": {}
      },
      "id": "45532578-da27-46ce-8d42-6ef715af3d01",
      "name": "Kirim Hasil Generate",
      "type": "n8n-nodes-base.telegram",
      "typeVersion": 1.1,
      "position": [
        944,
        -112
      ],
      "webhookId": "0023d7f7-c7e3-4570-82b1-55e7b906bccf",
      "credentials": {
        "telegramApi": {
          "id": "OrVOckaYs7PxxLt4",
          "name": "Telegram account"
        }
      }
    }
  ],
  "connections": {
    "Submit Text Prompt untuk Generate Gambar": {
      "main": [
        [
          {
            "node": "Mengirim Image Generation Request ke..",
            "type": "main",
            "index": 0
          }
        ]
      ]
    },
    "Mengirim Image Generation Request ke..": {
      "main": [
        [
          {
            "node": "Menunggu Proses Generate Gambar",
            "type": "main",
            "index": 0
          }
        ]
      ]
    },
    "Menunggu Proses Generate Gambar": {
      "main": [
        [
          {
            "node": "Mendapatkan Status Generate",
            "type": "main",
            "index": 0
          }
        ]
      ]
    },
    "Mendapatkan Status Generate": {
      "main": [
        [
          {
            "node": "Check Jika Generate Sudah Selesai",
            "type": "main",
            "index": 0
          }
        ]
      ]
    },
    "Check Jika Generate Sudah Selesai": {
      "main": [
        [
          {
            "node": "Format Result",
            "type": "main",
            "index": 0
          }
        ],
        [
          {
            "node": "Menunggu Proses Generate Gambar",
            "type": "main",
            "index": 0
          }
        ]
      ]
    },
    "Format Result": {
      "main": [
        [
          {
            "node": "Loop Image",
            "type": "main",
            "index": 0
          }
        ]
      ]
    },
    "Loop Image": {
      "main": [
        [
          {
            "node": "Download Gambar",
            "type": "main",
            "index": 0
          }
        ]
      ]
    },
    "Download Gambar": {
      "main": [
        [
          {
            "node": "Kirim Hasil Generate",
            "type": "main",
            "index": 0
          }
        ]
      ]
    }
  },
  "pinData": {},
  "meta": {
    "templateCredsSetupCompleted": true,
    "instanceId": "04b95c2f46319473af2c6f83e011a1ddc73025f83f7530dc90eb04615e801b58"
  }
}